{
  "id": "a38753e9-f1c2-47a4-8183-e943186896a1",
  "source": "fullfact",
  "source_name": "Full Fact (UK)",
  "collected_at": "2026-03-22T22:45:37.442815+00:00",
  "title": "Fake crash picture shared with false claims it shows satellite brought down by Iranian missile",
  "content": "Fake crash picture shared with false claims it shows satellite brought down by Iranian missile. A fake AI-generated image is being shared with false claims that Iranian missiles brought down a US-Israeli spy satellite. There are no reports of this happening.",
  "url": "https://fullfact.org/conflict/satellite-israel-iran-fake/",
  "tags": [
    "desinformação",
    "fact-check"
  ],
  "region_br": "internacional"
}